janis_bioinformatics/__init__.py
janis_bioinformatics/__meta__.py
janis_bioinformatics/data_types/__init__.py
janis_bioinformatics/data_types/bai.py
janis_bioinformatics/data_types/bam.py
janis_bioinformatics/data_types/bed.py
janis_bioinformatics/data_types/crai.py
janis_bioinformatics/data_types/cram.py
janis_bioinformatics/data_types/fasta.py
janis_bioinformatics/data_types/fastq.py
janis_bioinformatics/data_types/sam.py
janis_bioinformatics/data_types/tabix.py
janis_bioinformatics/data_types/vcf.py
janis_bioinformatics/tools/__init__.py
janis_bioinformatics/tools/bioinformaticstoolbase.py
janis_bioinformatics/tools/arriba/__init__.py
janis_bioinformatics/tools/arriba/base.py
janis_bioinformatics/tools/arriba/versions.py
janis_bioinformatics/tools/arriba/draw_fusions/__init__.py
janis_bioinformatics/tools/arriba/draw_fusions/base.py
janis_bioinformatics/tools/arriba/draw_fusions/versions.py
janis_bioinformatics/tools/arriba/run_arriba/__init__.py
janis_bioinformatics/tools/arriba/run_arriba/base.py
janis_bioinformatics/tools/arriba/run_arriba/versions.py
janis_bioinformatics/tools/babrahambioinformatics/__init__.py
janis_bioinformatics/tools/babrahambioinformatics/fastqc/__init__.py
janis_bioinformatics/tools/babrahambioinformatics/fastqc/base.py
janis_bioinformatics/tools/babrahambioinformatics/fastqc/basesingle.py
janis_bioinformatics/tools/babrahambioinformatics/fastqc/versions.py
janis_bioinformatics/tools/bcftools/__init__.py
janis_bioinformatics/tools/bcftools/bcftoolstoolbase.py
janis_bioinformatics/tools/bcftools/versions.py
janis_bioinformatics/tools/bcftools/annotate/__init__.py
janis_bioinformatics/tools/bcftools/annotate/base.py
janis_bioinformatics/tools/bcftools/annotate/versions.py
janis_bioinformatics/tools/bcftools/concat/__init__.py
janis_bioinformatics/tools/bcftools/concat/base.py
janis_bioinformatics/tools/bcftools/concat/versions.py
janis_bioinformatics/tools/bcftools/fill_from_fasta/__init__.py
janis_pipelines.bioinformatics-0.12.2.dist-info/LICENSE
janis_pipelines.bioinformatics-0.12.2.dist-info/METADATA
janis_pipelines.bioinformatics-0.12.2.dist-info/WHEEL
janis_pipelines.bioinformatics-0.12.2.dist-info/entry_points.txt
janis_pipelines.bioinformatics-0.12.2.dist-info/top_level.txt
janis_pipelines.bioinformatics-0.12.2.dist-info/RECORD
