Metadata-Version: 2.1
Name: janis-pipelines.bioinformatics
Version: 0.12.2
Summary: Bioinformatics tools for Janis; the Pipeline creation helper
Home-page: https://github.com/PMCC-BioinformaticsCore/janis-bioinformatics
Author: Michael Franklin, Evan Thomas, Mohammad Bhuyan
Author-email: michael.franklin@petermac.org
License: GNU
Platform: UNKNOWN
Classifier: Development Status :: 2 - Pre-Alpha
Classifier: Intended Audience :: Developers
Classifier: Intended Audience :: Science/Research
Classifier: Topic :: Scientific/Engineering :: Bio-Informatics
Requires-Dist: janis-pipelines.core (>=0.11.0)
Provides-Extra: ci
Requires-Dist: setuptools ; extra == 'ci'
Requires-Dist: wheel ; extra == 'ci'
Requires-Dist: twine ; extra == 'ci'
Provides-Extra: tests
Requires-Dist: nose ; extra == 'tests'
Requires-Dist: parameterized ; extra == 'tests'
Requires-Dist: janis-pipelines.unix (>=0.11.0) ; extra == 'tests'
Requires-Dist: janis-pipelines.runner (>=0.11.0) ; extra == 'tests'
